my_telugu_lib/__init__.py
my_telugu_lib/translator.py
my_telugu_lib/transliterator.py
my_telugu_lib/typing_tool.py
my_telugu_lib-1.0.0.dist-info/licenses/LICENSE
my_telugu_lib-1.0.0.dist-info/METADATA
my_telugu_lib-1.0.0.dist-info/WHEEL
my_telugu_lib-1.0.0.dist-info/entry_points.txt
my_telugu_lib-1.0.0.dist-info/top_level.txt
my_telugu_lib-1.0.0.dist-info/RECORD
