Metadata-Version: 2.4
Name: my_telugu_lib
Version: 1.0.0
Summary: Complete Telugu Translation & Transliteration Package with Built-in Typing Tool
Home-page: https://github.com/yourusername/my_telugu_lib
Author: Your Name
Author-email: your.email@example.com
Keywords: telugu translation transliteration indic language typing-tool
Classifier: Development Status :: 5 - Production/Stable
Classifier: Intended Audience :: Developers
Classifier: Topic :: Software Development :: Localization
Classifier: License :: OSI Approved :: MIT License
Classifier: Programming Language :: Python :: 3
Classifier: Programming Language :: Python :: 3.8
Classifier: Programming Language :: Python :: 3.9
Classifier: Programming Language :: Python :: 3.10
Classifier: Programming Language :: Python :: 3.11
Classifier: Programming Language :: Python :: 3.12
Classifier: Operating System :: OS Independent
Requires-Python: >=3.8
License-File: LICENSE
Requires-Dist: googletrans==4.0.0rc1
Requires-Dist: deep-translator
Requires-Dist: indic-transliteration
Dynamic: author
Dynamic: author-email
Dynamic: classifier
Dynamic: description
Dynamic: description-content-type
Dynamic: home-page
Dynamic: keywords
Dynamic: license-file
Dynamic: requires-dist
Dynamic: requires-python
Dynamic: summary
